sourcerat/__init__.py
sourcerat/__main__.py
sourcerat/cli.py
sourcerat/config.py
sourcerat/filters.py
sourcerat/gitignore.py
sourcerat/parser.py
sourcerat/renderer.py
sourcerat/scanner.py
sourcerat/sorter.py
sourcerat/tree.py
sourcerat-0.1.3.dist-info/WHEEL
sourcerat-0.1.3.dist-info/entry_points.txt
sourcerat-0.1.3.dist-info/METADATA
sourcerat-0.1.3.dist-info/RECORD
