Metadata-Version: 2.3
Name: sourcerat
Version: 0.1.3
Summary: Collect and bundle source code for LLM input
Author: Captain Solaris
Author-email: Captain Solaris <hello@spielprinzip.com>
Requires-Python: >=3.11
